{
  "player_id": "135922",
  "name": "YANG Yiyun",
  "english_name": "YANG Yiyun",
  "country": "CHN",
  "country_code": "CHN",
  "profile_url": "https://results.ittf.link/index.php/player-profile/list/60?resetfilters=1&vw_profiles___player_id_raw=135922&vw_profiles___Name_raw=YANG Yiyun",
  "rank": 72,
  "points": 369,
  "rank_change": 2,
  "scraped_at": "2026-04-14T16:20:11.009133",
  "gender": "Female",
  "birth_year": 2003,
  "age": 22,
  "style": "Right-Hand Defence (ShakeHand)",
  "playing_hand": "Right",
  "grip": "ShakeHand",
  "current_rank": 72,
  "ranking_week": "16/2026 (Apr 14th, 2026)",
  "career_best_rank": 47,
  "career_best_week": "8/2026",
  "career_stats": {
    "events": 32,
    "matches": 174,
    "wins": 136,
    "loses": 38,
    "wtt_senior_titles": 2,
    "all_senior_titles": 2
  },
  "current_year_stats": {
    "events": 2,
    "matches": 7,
    "wins": 6,
    "loses": 1,
    "games": 29,
    "games_won": 18,
    "games_lost": 11,
    "points_played": 519,
    "points_won": 264,
    "points_lost": 255,
    "wtt_senior_titles": 1,
    "all_senior_titles": 1
  },
  "recent_matches": [
    {
      "event": "WTT Feeder Doha 2026",
      "player": "YANG Yiyun",
      "player_country": "CHN",
      "opponent": "PARK Gahyeon",
      "opponent_country": "KOR",
      "stage": "WS Main Draw - Final",
      "score": "3 - 2 (8:11 11:7 6:11 11:1 11:7 )",
      "result": "WON"
    },
    {
      "event": "WTT Feeder Doha 2026",
      "player": "YANG Yiyun",
      "player_country": "CHN",
      "opponent": "HAN Feier",
      "opponent_country": "CHN",
      "stage": "WS Main Draw - SemiFinal",
      "score": "3 - 2 (6:11 13:11 11:5 3:11 11:4 )",
      "result": "WON"
    },
    {
      "event": "WTT Feeder Doha 2026",
      "player": "QIN Yuxuan",
      "player_country": "CHN",
      "opponent": "YANG Yiyun",
      "opponent_country": "CHN",
      "stage": "WS Main Draw - QuarterFinal",
      "score": "1 - 3 (11:3 7:11 11:13 6:11 )",
      "result": "WON"
    },
    {
      "event": "WTT Feeder Doha 2026",
      "player": "SER Lin Qian",
      "player_country": "SGP",
      "opponent": "YANG Yiyun",
      "opponent_country": "CHN",
      "stage": "WS Main Draw - R16",
      "score": "1 - 3 (11:4 9:11 11:13 9:11 )",
      "result": "WON"
    },
    {
      "event": "WTT Feeder Doha 2026",
      "player": "KONG Tsz Lam",
      "player_country": "HKG",
      "opponent": "YANG Yiyun",
      "opponent_country": "CHN",
      "stage": "WS Main Draw - R32",
      "score": "0 - 3 (7:11 10:12 4:11 )",
      "result": "WON"
    },
    {
      "event": "WTT Contender Muscat 2026",
      "player": "YANG Yiyun",
      "player_country": "CHN",
      "opponent": "CHENG I-Ching",
      "opponent_country": "TPE",
      "stage": "WS Main Draw - R16",
      "score": "0 - 3 (5:11 6:11 5:11 )",
      "result": "LOST"
    }
  ],
  "avatar_url": "https://wttsimfiles.blob.core.windows.net/wtt-media/photos/400px/Headshot_R_YANG_Yiyun.png",
  "avatar_file_path": "data\\player_avatars\\player_135922_YANG_Yiyun.png"
}