{
  "player_id": "120187",
  "name": "LUPULESKU Izabela",
  "english_name": "LUPULESKU Izabela",
  "country": "塞尔维亚",
  "country_code": "SRB",
  "profile_url": "https://results.ittf.link/index.php/player-profile/list/60?resetfilters=1&vw_profiles___player_id_raw=120187&vw_profiles___Name_raw=LUPULESKU Izabela",
  "rank": 85,
  "points": 310,
  "rank_change": -1,
  "scraped_at": "2026-04-14T16:23:47.932481",
  "gender": "女",
  "birth_year": 1999,
  "age": 26,
  "style": "右手进攻型(横拍)",
  "playing_hand": "右手",
  "grip": "横拍",
  "current_rank": 85,
  "ranking_week": "16/2026 (Apr 14th, 2026)",
  "career_best_rank": 69,
  "career_best_week": "19/2025",
  "career_stats": {
    "events": 142,
    "matches": 628,
    "wins": 369,
    "loses": 259,
    "wtt_senior_titles": 0,
    "all_senior_titles": 0
  },
  "current_year_stats": {
    "events": 4,
    "matches": 8,
    "wins": 4,
    "loses": 4,
    "games": 32,
    "games_won": 16,
    "games_lost": 16,
    "points_played": 617,
    "points_won": 313,
    "points_lost": 304,
    "wtt_senior_titles": 0,
    "all_senior_titles": 0
  },
  "avatar_url": "https://wttsimfiles.blob.core.windows.net/wtt-media/photos/400px/120187_Headshot_R_ LUPULESKU_Izabela.png",
  "avatar_file_path": "data\\player_avatars\\player_120187_LUPULESKU_Izabela.png"
}